{
  "properties": {
    "connectionReferences": {
      "shared_commondataserviceforapps": {
        "api": {
          "name": "shared_commondataserviceforapps"
        },
        "connection": {
          "connectionReferenceLogicalName": "alm_sharedcommondataserviceforapps_ae209"
        },
        "runtimeSource": "embedded"
      },
      "shared_gmail": {
        "api": {
          "name": "shared_gmail"
        },
        "connection": {
          "connectionReferenceLogicalName": "alm_sharedgmail_6aafe"
        },
        "runtimeSource": "embedded"
      }
    },
    "definition": {
      "$schema": "https://schema.management.azure.com/providers/Microsoft.Logic/schemas/2016-06-01/workflowdefinition.json#",
      "contentVersion": "1.0.0.0",
      "parameters": {
        "$authentication": {
          "defaultValue": {},
          "type": "SecureObject"
        },
        "$connections": {
          "defaultValue": {},
          "type": "Object"
        }
      },
      "triggers": {
        "When_a_row_is_added,_modified_or_deleted": {
          "type": "OpenApiConnectionWebhook",
          "inputs": {
            "parameters": {
              "subscriptionRequest/message": 4,
              "subscriptionRequest/entityname": "alm_timeoffrequests",
              "subscriptionRequest/scope": 4
            },
            "host": {
              "apiId": "/providers/Microsoft.PowerApps/apis/shared_commondataserviceforapps",
              "operationId": "SubscribeWebhookTrigger",
              "connectionName": "shared_commondataserviceforapps"
            }
          },
          "metadata": {
            "operationMetadataId": "d5755184-f319-46ff-bf76-9de607aeec40"
          }
        }
      },
      "actions": {
        "Condition": {
          "type": "If",
          "expression": {
            "or": [
              {
                "equals": [
                  "@triggerOutputs()?['body/alm_approved']",
                  "@equals(triggerOutputs()?['body/alm_approved'], true)"
                ]
              }
            ]
          },
          "actions": {
            "Send_email_(V2)": {
              "type": "OpenApiConnection",
              "inputs": {
                "parameters": {
                  "emailMessage/To": "@triggerOutputs()?['body/alm_empemail']",
                  "emailMessage/Subject": "Leave Request is approved",
                  "emailMessage/Body": "<p>Your Leave Request is approved by Manager.</p>"
                },
                "host": {
                  "apiId": "/providers/Microsoft.PowerApps/apis/shared_gmail",
                  "operationId": "SendEmailV2",
                  "connectionName": "shared_gmail"
                }
              },
              "metadata": {
                "operationMetadataId": "55391e9f-25fd-42ac-bd42-59e8f853111f"
              }
            }
          },
          "else": {
            "actions": {}
          },
          "runAfter": {}
        }
      }
    },
    "templateName": null
  },
  "schemaVersion": "1.0.0.0"
}